Metadata-Version: 2.1
Name: quickinfo
Version: 2.1.0
Summary: A library that scrapes data from google webpages
Home-page: https://github.com/darkskyprogrammers/quick-info
Author: DarkSky (Arya P. and Ananthram V.)
Author-email: darkskyprogrammers@gmail.com
License: UNKNOWN
Keywords: quickinfo,quickinfo 2,python,quick info,quick scrape,google,search,scrape,quickscrape
Platform: UNKNOWN
Classifier: Development Status :: 1 - Planning
Classifier: Intended Audience :: Developers
Classifier: Programming Language :: Python :: 3.6
Classifier: Programming Language :: Python :: 3.7
Classifier: Programming Language :: Python :: 3.8
Classifier: Operating System :: Unix
Classifier: Operating System :: MacOS :: MacOS X
Classifier: Operating System :: Microsoft :: Windows
